portainer_deployer/.env.example
portainer_deployer/__init__.py
portainer_deployer/app.conf.example
portainer_deployer/app.py
portainer_deployer/info.json
portainer_deployer/config/__init__.py
portainer_deployer/config/config.py
portainer_deployer/utils/__init__.py
portainer_deployer/utils/utils.py
portainer_deployer-0.0.6.dist-info/LICENSE
portainer_deployer-0.0.6.dist-info/METADATA
portainer_deployer-0.0.6.dist-info/WHEEL
portainer_deployer-0.0.6.dist-info/entry_points.txt
portainer_deployer-0.0.6.dist-info/top_level.txt
portainer_deployer-0.0.6.dist-info/RECORD
