Metadata-Version: 2.1
Name: portainer-deployer
Version: 0.0.6
Summary: A command-line tool to abstract some Portainer's features by using its API.
Home-page: https://github.com/Jorgmassih/portainer-deployer
Author: Jorge A. Massih
Author-email: jorgmassih@gmail.com
Project-URL: Bug Tracker, https://github.com/Jorgmassih/portainer-deployer/issues
Classifier: Programming Language :: Python :: 3
Classifier: License :: OSI Approved :: MIT License
Classifier: Operating System :: Unix
Classifier: Development Status :: 3 - Alpha
Classifier: Environment :: Console
Classifier: Intended Audience :: System Administrators
Classifier: Natural Language :: English
Classifier: Topic :: System :: Systems Administration
Classifier: Topic :: System :: Installation/Setup
Requires-Python: >=3.8.0
License-File: LICENSE
Requires-Dist: PyYAML (~=6.0)
Requires-Dist: requests (~=2.27.1)
